{"B0210": "เซลเอก", "B0226": "เซลพัด", "B0227": "เซลจ๋า", "B0230": "เซลบอม", "B0248": "เซลแอน BKK", "B0253": "เซลอร", "B0223": "เซลนุช", "C0219": "เซลแอน UC", "C0233": "เซลที", "C0239": "เซลไอซ์", "C0244": "เซลหนุ่ย", "C0247": "เซลบ๋อมแบ๋ม", "C0249": "เซลบี", "C0209": "ส่วนกลาง", "3BV": "3BV", "Walk-in Customers": "ส่วนกลาง", "3GLAZZIQ": "3GLAZZIQ", "BD": "BD", "BTV": "", "BTVFC": "", "99": "Balance/หน่วยรถ", "E-Coupon": "E-Coupon", "B0410": "Liew Kit Ping", "Lens": "", "Sale code": "Nick name", "B0213": "เซลน้อง", "B0238": "เซลเป้", "B0243": "เซลต่าย", "B0250": "เซลมิ้น", "B0242": "", "B0247": "เซลหม่อน", "B0249": "เซลมิก", "C0224": "เซลโม", "C0240": "เซลเอื้อง", "C0241": "เซลแตง", "C0242": "เซลรี", "Lens unknown salesperosn": "", "C2040": "เซลเอื้อง", "C2041": "เซลแตง", "C0232": "", "CS": "", "เซลล์ Alcon": "", "B0401": "เซลเปิ้ล ALCON", "B0402": "เซลโฟค ALCON", "B0403": "เซลเนตร ALCON", "B0404": "เซลอัญ ALCON", "B0405": "เซลแอน ALCON", "B0406": "เซลรี ALCON", "B0407": "เซลติ๊ก ALCON", "C0401": "เซลแยม ALCON", "B0208": "เซลเล็ก", "B0240": "เซลเมย์", "B0221": "เซลชัย", "B0231": "เซลกี้", "B0251": "เซลโบ๊ท", "B0245": "เซลก้อย", "B0246": "เซลแอ้ม", "C0218": "เซลอั๋น", "C0227": "เซลเกียรติ", "C0229": "เซลหงษ์", "C0231": "เซลแซม", "C0235": "เซลโดม", "C0223": "เซลนิด", "C0225": "เซลล์เบียร์", "C0226": "เซลล์หนึ่ง", "B0252": "เซลเมย์", "C0243": "เซลต้น", "C0236": "เซลแนท", "C0246": "เซลใหม่", "B0254": "เซลหน่อง", "B0255": "เซลแทน", "Code": "Type", "1": "Non BTV", "2": "Non BTV", "3": "Non BTV", "4": "BTV", "5": "BTV", "6": "Non BTV", "W": "Non BTV", "Quarter": "Month", "Q1": "Mar", "Q2": "Jun", "Q3": "Sep", "Q4": "Dec"}